orjson/__init__.py
orjson/__init__.pyi
orjson/orjson.cpython-314-arm-linux-gnueabihf.so
orjson/py.typed
orjson_twy-3.11.5.post1.dist-info/METADATA
orjson_twy-3.11.5.post1.dist-info/WHEEL
orjson_twy-3.11.5.post1.dist-info/licenses/LICENSE-APACHE
orjson_twy-3.11.5.post1.dist-info/licenses/LICENSE-MIT
orjson_twy-3.11.5.post1.dist-info/RECORD
